processor.py
kkutils-1.7.7.data/data/requirements.txt
tornado_utils/__init__.py
tornado_utils/application.py
tornado_utils/basehandler.py
tornado_utils/userhandler.py
tornado_utils/utils.py
utils/__init__.py
utils/base_utils.py
utils/cached_property.py
utils/config_utils.py
utils/crypto.py
utils/curl_utils.py
utils/db_utils.py
utils/decorator.py
utils/email_utils.py
utils/fire.py
utils/http_utils.py
utils/log_utils.py
utils/rabbitmq.py
utils/stopwatch.py
utils/xdb_searcher.py
kkutils-1.7.7.dist-info/METADATA
kkutils-1.7.7.dist-info/WHEEL
kkutils-1.7.7.dist-info/top_level.txt
kkutils-1.7.7.dist-info/RECORD
