Metadata-Version: 2.2
Name: kkutils
Version: 1.7.7
Summary: python utils
Home-page: https://www.github.com
Author: digua
Author-email: digua@gmail.com
License: MIT
Classifier: Development Status :: 4 - Beta
Classifier: Intended Audience :: Developers
Classifier: Topic :: Software Development :: Build Tools
Classifier: License :: OSI Approved :: MIT License
Classifier: Programming Language :: Python :: 3.6
Classifier: Programming Language :: Python :: 3.7
Classifier: Programming Language :: Python :: 3.8
Classifier: Programming Language :: Python :: 3.9
Classifier: Programming Language :: Python :: 3.10
Classifier: Programming Language :: Python :: 3.11
Requires-Python: >=3.6
Requires-Dist: aio-pika
Requires-Dist: aiohttp<=3.9.5
Requires-Dist: aiomysql
Requires-Dist: aiosmtplib
Requires-Dist: apscheduler
Requires-Dist: beautifulsoup4
Requires-Dist: chardet
Requires-Dist: coloredlogs
Requires-Dist: dbutils
Requires-Dist: hiredis
Requires-Dist: html5lib
Requires-Dist: lxml
Requires-Dist: motor
Requires-Dist: pika
Requires-Dist: pybase62
Requires-Dist: pycryptodome
Requires-Dist: pycryptodomex
Requires-Dist: pymongo
Requires-Dist: pyyaml
Requires-Dist: redis
Requires-Dist: requests-toolbelt
Requires-Dist: requests[socks]
Requires-Dist: rich
Requires-Dist: rsa
Requires-Dist: tld
Requires-Dist: tornado
Requires-Dist: tqdm
Requires-Dist: uvloop
Provides-Extra: curl
Requires-Dist: pycurl; extra == "curl"
Dynamic: author
Dynamic: author-email
Dynamic: classifier
Dynamic: home-page
Dynamic: license
Dynamic: provides-extra
Dynamic: requires-dist
Dynamic: requires-python
Dynamic: summary
